src/__init__.py
src/apps.py
cashho-1.0.dist-info/METADATA
cashho-1.0.dist-info/WHEEL
cashho-1.0.dist-info/top_level.txt
cashho-1.0.dist-info/RECORD
