Metadata-Version: 2.1
Name: cashho
Version: 1.0
Requires-Dist: Django (>=3.2)
